README.md
setup.py
AQN/__init__.py
AQN/module_python_1.py
aqn.egg-info/PKG-INFO
aqn.egg-info/SOURCES.txt
aqn.egg-info/dependency_links.txt
aqn.egg-info/top_level.txt