Metadata-Version: 2.1
Name: aqn
Version: 0.1.0
Summary: AQN Meme Package
Home-page: https://github.com/lyhryn/python-py
Author: lyryhn
Author-email: donttrytodoxme@gmail.com
License: UNKNOWN
Platform: UNKNOWN
Classifier: Development Status :: 1 - Planning
Classifier: Intended Audience :: Science/Research
Classifier: Programming Language :: Python :: 2
Classifier: Programming Language :: Python :: 2.7
Classifier: Programming Language :: Python :: 3
Classifier: Programming Language :: Python :: 3.4
Classifier: Programming Language :: Python :: 3.5
